nfl_api_client/__init__.py
nfl_api_client/_scripts/__init__.py
nfl_api_client/_scripts/generate_players.py
nfl_api_client/data_sets/__init__.py
nfl_api_client/data_sets/dataset.py
nfl_api_client/data_sets/dataset_container.py
nfl_api_client/endpoints/__init__.py
nfl_api_client/endpoints/_base.py
nfl_api_client/endpoints/game_officials.py
nfl_api_client/endpoints/game_scoring_plays.py
nfl_api_client/endpoints/league_standings.py
nfl_api_client/endpoints/player_gamelog.py
nfl_api_client/endpoints/season_standings.py
nfl_api_client/endpoints/stats_leaders.py
nfl_api_client/endpoints/team_depth_chart.py
nfl_api_client/endpoints/team_roster.py
nfl_api_client/endpoints/team_schedule.py
nfl_api_client/http_client/__init__.py
nfl_api_client/http_client/request_service.py
nfl_api_client/lib/__init__.py
nfl_api_client/lib/data.py
nfl_api_client/lib/endpoint_registry.py
nfl_api_client/lib/parameters.py
nfl_api_client/lib/response_parsers/__init__.py
nfl_api_client/lib/response_parsers/game_officials.py
nfl_api_client/lib/response_parsers/game_scoring_plays.py
nfl_api_client/lib/response_parsers/player_gamelog.py
nfl_api_client/lib/response_parsers/season_standings.py
nfl_api_client/lib/response_parsers/stats_leaders.py
nfl_api_client/lib/response_parsers/team_depth_chart.py
nfl_api_client/lib/response_parsers/team_roster.py
nfl_api_client/lib/response_parsers/team_schedule.py
nfl_api_client/lib/utils.py
nfl_api_client/static/players.py
nfl_api_client-1.0.1.dist-info/METADATA
nfl_api_client-1.0.1.dist-info/WHEEL
nfl_api_client-1.0.1.dist-info/RECORD
