Metadata-Version: 2.3
Name: nfl-api-client
Version: 1.0.1
Summary: Client package for accessing NFL data available on ESPN's API endpoints
License: MIT
Keywords: nfl,espn,api,football,sports,betting
Author: Hayden D'Souza haydenfds@gmail.com
Requires-Python: >=3.9
Classifier: License :: OSI Approved :: MIT License
Classifier: Programming Language :: Python :: 3
Classifier: Programming Language :: Python :: 3.9
Classifier: Programming Language :: Python :: 3.10
Classifier: Programming Language :: Python :: 3.11
Classifier: Programming Language :: Python :: 3.12
Classifier: Programming Language :: Python :: 3.13
Requires-Dist: httpx (>=0.28.1,<0.29.0)
Requires-Dist: pandas (>=2.3.0,<3.0.0)
Project-URL: Documentation, https://nfl-api-client.readthedocs.io/en/latest/
Project-URL: Repository, https://github.com/haydenfd/nfl_api_client
